blurr/VERSION
blurr/__init__.py
blurr/__main__.py
blurr/cli/__init__.py
blurr/cli/cli.py
blurr/cli/package_spark.py
blurr/cli/transform.py
blurr/cli/util.py
blurr/cli/validate.py
blurr/core/__init__.py
blurr/core/aggregate.py
blurr/core/aggregate_activity.py
blurr/core/aggregate_block.py
blurr/core/aggregate_identity.py
blurr/core/aggregate_time.py
blurr/core/aggregate_variable.py
blurr/core/aggregate_window.py
blurr/core/anchor.py
blurr/core/base.py
blurr/core/errors.py
blurr/core/evaluation.py
blurr/core/field.py
blurr/core/field_complex.py
blurr/core/field_simple.py
blurr/core/loader.py
blurr/core/logging.py
blurr/core/record.py
blurr/core/schema_context.py
blurr/core/schema_loader.py
blurr/core/store.py
blurr/core/store_key.py
blurr/core/transformer.py
blurr/core/transformer_streaming.py
blurr/core/transformer_window.py
blurr/core/type.py
blurr/core/validator.py
blurr/runner/__init__.py
blurr/runner/data_processor.py
blurr/runner/json_encoder.py
blurr/runner/local_runner.py
blurr/runner/runner.py
blurr/runner/spark_runner.py
blurr/store/__init__.py
blurr/store/dynamo_store.py
blurr/store/memory_store.py
blurr-0.4.1.data/data/VERSION
blurr-0.4.1.dist-info/METADATA
blurr-0.4.1.dist-info/RECORD
blurr-0.4.1.dist-info/WHEEL
blurr-0.4.1.dist-info/entry_points.txt
blurr-0.4.1.dist-info/top_level.txt
