Metadata-Version: 2.1
Name: blurr
Version: 0.4.1
Summary: Data aggregation pipeline for running real-time predictive models
Home-page: https://github.com/productml/blurr
Author: productml.com
Author-email: info@productml.com
License: UNKNOWN
Platform: UNKNOWN
Classifier: Development Status :: 1 - Planning
Classifier: Intended Audience :: Developers
Classifier: Intended Audience :: Science/Research
Classifier: License :: OSI Approved :: Apache Software License
Classifier: Operating System :: OS Independent
Classifier: Topic :: Scientific/Engineering :: Artificial Intelligence
Classifier: Topic :: Software Development :: Libraries :: Python Modules
Classifier: Programming Language :: Python :: 3
Classifier: Programming Language :: Python :: 3.6
Classifier: Programming Language :: Python :: 3 :: Only
Requires-Python: >=3.6
Requires-Dist: pyyaml
Requires-Dist: python-dateutil
Requires-Dist: docopt
Requires-Dist: boto3
Requires-Dist: smart-open
